{
  "filename": "0afda461-82c1-4089-9428-ef3d6d3668ac-damage-photo04-01-P6-AT-V1.jpg",
  "annotation_timestamp": "2026-06-24T14:41:35.708010",
  "annotation_source": "tab1",
  "annotation_model_name": "Référence unique (best_2.pt)",
  "annotation_model_path": "best_2.pt",
  "annotation_model_classes": [
    {
      "id": 0,
      "name": "crack",
      "dataset_id": 0,
      "dataset_name": "crack"
    },
    {
      "id": 1,
      "name": "dent",
      "dataset_id": 1,
      "dataset_name": "dent"
    },
    {
      "id": 2,
      "name": "glass shatter",
      "dataset_id": 2,
      "dataset_name": "glass shatter"
    },
    {
      "id": 3,
      "name": "lamp broken",
      "dataset_id": 3,
      "dataset_name": "lamp broken"
    },
    {
      "id": 4,
      "name": "scratch",
      "dataset_id": 4,
      "dataset_name": "scratch"
    },
    {
      "id": 5,
      "name": "tire flat",
      "dataset_id": 5,
      "dataset_name": "tire flat"
    }
  ],
  "annotation_boxes_count": 7,
  "annotation_masks_count": 0,
  "annotation_contains_manual_boxes": false,
  "requires_final_harmonization": false,
  "non_final_classes_present": [],
  "final_dataset_classes": {
    "0": "crack",
    "1": "dent",
    "2": "glass shatter",
    "3": "lamp broken",
    "4": "scratch",
    "5": "tire flat"
  },
  "dataset_class_standard": "best_2 canonical: 0=crack, 1=dent, 2=glass shatter, 3=lamp broken, 4=scratch, 5=tire flat",
  "boxes": [
    {
      "class_id": 4,
      "class_name": "scratch",
      "class_display": "Rayure (Scratch)",
      "source_model_class_id": null,
      "source_model_class_name": null,
      "confidence": 1.0,
      "bbox_pixels": {
        "x1": 150,
        "y1": 358,
        "x2": 337,
        "y2": 400
      },
      "bbox_yolo": {
        "x_center": 0.601235,
        "y_center": 0.450119,
        "width": 0.461728,
        "height": 0.049881
      }
    },
    {
      "class_id": 4,
      "class_name": "scratch",
      "class_display": "Rayure (Scratch)",
      "source_model_class_id": null,
      "source_model_class_name": null,
      "confidence": 1.0,
      "bbox_pixels": {
        "x1": 138,
        "y1": 238,
        "x2": 206,
        "y2": 284
      },
      "bbox_yolo": {
        "x_center": 0.424691,
        "y_center": 0.309976,
        "width": 0.167901,
        "height": 0.054632
      }
    },
    {
      "class_id": 4,
      "class_name": "scratch",
      "class_display": "Rayure (Scratch)",
      "source_model_class_id": null,
      "source_model_class_name": null,
      "confidence": 1.0,
      "bbox_pixels": {
        "x1": 127,
        "y1": 274,
        "x2": 209,
        "y2": 360
      },
      "bbox_yolo": {
        "x_center": 0.414815,
        "y_center": 0.376485,
        "width": 0.202469,
        "height": 0.102138
      }
    },
    {
      "class_id": 4,
      "class_name": "scratch",
      "class_display": "Rayure (Scratch)",
      "source_model_class_id": null,
      "source_model_class_name": null,
      "confidence": 1.0,
      "bbox_pixels": {
        "x1": 244,
        "y1": 232,
        "x2": 288,
        "y2": 344
      },
      "bbox_yolo": {
        "x_center": 0.65679,
        "y_center": 0.342043,
        "width": 0.108642,
        "height": 0.133017
      }
    },
    {
      "class_id": 4,
      "class_name": "scratch",
      "class_display": "Rayure (Scratch)",
      "source_model_class_id": null,
      "source_model_class_name": null,
      "confidence": 1.0,
      "bbox_pixels": {
        "x1": 62,
        "y1": 516,
        "x2": 234,
        "y2": 609
      },
      "bbox_yolo": {
        "x_center": 0.365432,
        "y_center": 0.668052,
        "width": 0.424691,
        "height": 0.110451
      }
    },
    {
      "class_id": 4,
      "class_name": "scratch",
      "class_display": "Rayure (Scratch)",
      "source_model_class_id": null,
      "source_model_class_name": null,
      "confidence": 1.0,
      "bbox_pixels": {
        "x1": 115,
        "y1": 643,
        "x2": 191,
        "y2": 664
      },
      "bbox_yolo": {
        "x_center": 0.377778,
        "y_center": 0.776128,
        "width": 0.187654,
        "height": 0.024941
      }
    },
    {
      "class_id": 1,
      "class_name": "dent",
      "class_display": "Bosse (Dent)",
      "source_model_class_id": null,
      "source_model_class_name": null,
      "confidence": 1.0,
      "bbox_pixels": {
        "x1": 117,
        "y1": 408,
        "x2": 267,
        "y2": 577
      },
      "bbox_yolo": {
        "x_center": 0.474074,
        "y_center": 0.584917,
        "width": 0.37037,
        "height": 0.200713
      }
    }
  ],
  "session_name": "session_20260624_142024"
}